twitter.common.config-0.3.11-py2.7-nspkg.pth
twitter/common/config/__init__.py
twitter/common/config/properties.py
twitter.common.config-0.3.11.dist-info/DESCRIPTION.rst
twitter.common.config-0.3.11.dist-info/METADATA
twitter.common.config-0.3.11.dist-info/RECORD
twitter.common.config-0.3.11.dist-info/WHEEL
twitter.common.config-0.3.11.dist-info/metadata.json
twitter.common.config-0.3.11.dist-info/namespace_packages.txt
twitter.common.config-0.3.11.dist-info/top_level.txt
twitter.common.config-0.3.11.dist-info/zip-safe
