Metadata-Version: 2.0
Name: twitter.common.config
Version: 0.3.11
Summary: twitter.common config parsing library.
Home-page: https://github.com/twitter/commons
Author: UNKNOWN
Author-email: UNKNOWN
License: Apache License, Version 2.0
Platform: UNKNOWN
Classifier: Intended Audience :: Developers
Classifier: License :: OSI Approved :: Apache Software License
Classifier: Operating System :: OS Independent
Classifier: Programming Language :: Python
Requires-Dist: twitter.common.collections (==0.3.11)
Requires-Dist: twitter.common.lang (==0.3.11)
